porobot/__init__.py
porobot/api/__init__.py
porobot/api/normal.py
porobot/core/__init__.py
porobot/lib/__init__.py
porobot-0.0.3.dist-info/LICENSE
porobot-0.0.3.dist-info/METADATA
porobot-0.0.3.dist-info/WHEEL
porobot-0.0.3.dist-info/top_level.txt
porobot-0.0.3.dist-info/RECORD
