Metadata-Version: 2.1
Name: porobot
Version: 0.0.3
Summary: pip install porobot
Home-page: https://www.python-office.com/
Author: CoderWanFeng
Author-email: 1957875073@qq.com
License: MIT
Project-URL: Bug Tracker, https://github.com/CoderWanFeng/porobot/issues
Project-URL: Documentation, https://github.com/CoderWanFeng/porobot/blob/master/README.md
Project-URL: Source Code, https://github.com/CoderWanFeng/porobot
Platform: any
Requires-Python: >=3.5
License-File: LICENSE
Requires-Dist: akshare
